termoscart/__init__.py
termoscart/__main__.py
termoscart/cliplot.py
termoscart/f.py
termoscart-0.1.2.dist-info/LICENSE
termoscart-0.1.2.dist-info/METADATA
termoscart-0.1.2.dist-info/WHEEL
termoscart-0.1.2.dist-info/entry_points.txt
termoscart-0.1.2.dist-info/RECORD
