Metadata-Version: 2.3
Name: termoscart
Version: 0.1.2
Summary: Terminal Oscilloscope Art - Bringing beautiful, animated curves to the command line
License: GPL-3.0-only
Author: Kevin Golob
Author-email: 151143873+kvnglb@users.noreply.github.com
Requires-Python: >=3.8.1
Classifier: Development Status :: 4 - Beta
Classifier: Environment :: Console
Classifier: License :: OSI Approved :: GNU General Public License v3 (GPLv3)
Classifier: Operating System :: OS Independent
Classifier: Programming Language :: Python :: 3 :: Only
Classifier: Topic :: Games/Entertainment :: Simulation
Classifier: Topic :: Scientific/Engineering :: Visualization
Project-URL: Homepage, https://github.com/kvnglb/termoscart
Project-URL: Repository, https://github.com/kvnglb/termoscart
